Dtime/Dtime.py
Dtime/__init__.py
Dtime-0.3.dist-info/METADATA
Dtime-0.3.dist-info/WHEEL
Dtime-0.3.dist-info/top_level.txt
Dtime-0.3.dist-info/RECORD
