Metadata-Version: 2.1
Name: Dtime
Version: 0.3
Summary: discord uptime
Home-page: https://github.com/0xfmc/Dtime/blob/master/Dtime.py
Author: admin_01S
Author-email: discord-api@naver.com
License: MIT
Platform: UNKNOWN
Classifier: Programming Language :: Python :: 3.6
Classifier: Programming Language :: Python :: 3.7
Classifier: Programming Language :: Python :: 3.8
Requires-Python: >=3.6
